sendria/__init__.py
sendria/__main__.py
sendria/build_assets.py
sendria/callback.py
sendria/cli.py
sendria/config.py
sendria/db.py
sendria/errors.py
sendria/message.py
sendria/smtp.py
sendria/http/__init__.py
sendria/http/core.py
sendria/http/json_encoder.py
sendria/http/middlewares.py
sendria/http/notifier.py
sendria/static/.webassets-cache/08b6afb13186169fc95503de9081b865
sendria/static/.webassets-cache/36535012ceb97e120ae27dd5f8b8dfa3
sendria/static/.webassets-cache/41ff6171a7e0c4605a56f50dadd5504c
sendria/static/.webassets-cache/5faada0de0729c164ea3e80b7109cd1b
sendria/static/.webassets-cache/894b602483deac47fd57977d44b6d854
sendria/static/.webassets-cache/9520ecff04dbdd37837a54fe798724f5
sendria/static/.webassets-cache/b9c26fdd3dcd2691d294e6b0e7773b4e
sendria/static/.webassets-cache/c79be72c800f595779c0947a800967f4
sendria/static/.webassets-cache/ef8ab52c6cfef1f158090f2c30bbe54f
sendria/static/assets/bundle.a6ae6674.css
sendria/static/assets/bundle.f22b5981.js
sendria/static/assets/sendria.55b2bd8a.css
sendria/static/assets/sendria.66d54899.css
sendria/static/assets/sendria.a2408e62.css
sendria/static/assets/sendria.d944bbc5.css
sendria/static/assets/sendria.fd73cb12.css
sendria/static/css/jquery-ui.css
sendria/static/css/reset.css
sendria/static/css/sendria.scss
sendria/static/images/icon_128x128.png
sendria/static/images/icon_32x32.png
sendria/static/images/jquery-ui/animated-overlay.gif
sendria/static/images/jquery-ui/ui-bg_diagonals-thick_50_aaaaaa_40x40.png
sendria/static/images/jquery-ui/ui-bg_flat_0_aaaaaa_40x100.png
sendria/static/images/jquery-ui/ui-bg_flat_75_ffffff_40x100.png
sendria/static/images/jquery-ui/ui-bg_glass_55_fbf9ee_1x400.png
sendria/static/images/jquery-ui/ui-bg_glass_65_ffffff_1x400.png
sendria/static/images/jquery-ui/ui-bg_glass_75_dadada_1x400.png
sendria/static/images/jquery-ui/ui-bg_glass_75_e6e6e6_1x400.png
sendria/static/images/jquery-ui/ui-bg_glass_95_fef1ec_1x400.png
sendria-2.2.2.dist-info/LICENSE
sendria-2.2.2.dist-info/METADATA
sendria-2.2.2.dist-info/WHEEL
sendria-2.2.2.dist-info/entry_points.txt
sendria-2.2.2.dist-info/top_level.txt
sendria-2.2.2.dist-info/RECORD
