Metadata-Version: 2.1
Name: sendria
Version: 2.2.2
Summary: An SMTP server that makes all received mails accessible via a web interface and REST API.
Home-page: https://github.com/msztolcman/sendria
Author: Marcin Sztolcman
Author-email: marcin@urzenia.net
License: MIT
Download-URL: https://github.com/msztolcman/sendria
Project-URL: GitHub: issues, https://github.com/msztolcman/sendria/issues
Project-URL: GitHub: repo, https://github.com/msztolcman/sendria
Platform: UNKNOWN
Classifier: Development Status :: 4 - Beta
Classifier: Programming Language :: Python
Classifier: Programming Language :: Python :: 3
Classifier: Programming Language :: Python :: 3.7
Classifier: Programming Language :: Python :: 3.8
Classifier: Programming Language :: Python :: 3.9
Classifier: Environment :: No Input/Output (Daemon)
Classifier: Environment :: Web Environment
Classifier: Intended Audience :: Developers
Classifier: Intended Audience :: System Administrators
Classifier: License :: OSI Approved :: MIT License
Classifier: Operating System :: POSIX
Classifier: Operating System :: MacOS :: MacOS X
Classifier: Topic :: Communications :: Email
Classifier: Topic :: Software Development
Classifier: Topic :: System :: Networking
Classifier: Topic :: Utilities
Classifier: Framework :: AsyncIO
Requires-Python: >=3.7
Requires-Dist: aiohttp
Requires-Dist: aiohttp-basicauth
Requires-Dist: aiohttp-jinja2
Requires-Dist: aiosmtpd (>=1.4.2)
Requires-Dist: aiosqlite
Requires-Dist: beautifulsoup4
Requires-Dist: cssmin
Requires-Dist: fileperms
Requires-Dist: html5lib
Requires-Dist: lockfile
Requires-Dist: passlib
Requires-Dist: python-daemon
Requires-Dist: pytz
Requires-Dist: pyscss
Requires-Dist: structlog (>=21.1.0)
Requires-Dist: toml
Requires-Dist: webassets
